zerial/__init__.py
zerial/_base.py
zerial/_compat.py
zerial/_core.py
zerial/_data.py
zerial/numpy.py
zerial-0.2.1.dist-info/AUTHORS.rst
zerial-0.2.1.dist-info/LICENSE
zerial-0.2.1.dist-info/METADATA
zerial-0.2.1.dist-info/WHEEL
zerial-0.2.1.dist-info/top_level.txt
zerial-0.2.1.dist-info/RECORD
