Metadata-Version: 2.1
Name: zerial
Version: 0.2.1
Summary: Stuct and destructure complex classes
Home-page: https://github.com/jriddy/zerial
Author: Josh Reed
Author-email: jriddy@gmail.com
License: MIT
Keywords: zerial
Platform: UNKNOWN
Classifier: Development Status :: 2 - Pre-Alpha
Classifier: Intended Audience :: Developers
Classifier: License :: OSI Approved :: MIT License
Classifier: Natural Language :: English
Classifier: Programming Language :: Python :: 2
Classifier: Programming Language :: Python :: 2.7
Classifier: Programming Language :: Python :: 3
Classifier: Programming Language :: Python :: 3.5
Classifier: Programming Language :: Python :: 3.6
Classifier: Programming Language :: Python :: 3.7
Requires-Dist: attrs
Requires-Dist: enum ; python_version < "3.4"
Requires-Dist: typing ; python_version < "3.5"
Provides-Extra: dev
Requires-Dist: numpy ; extra == 'dev'
Requires-Dist: pytest ; extra == 'dev'
Requires-Dist: pytest-mock ; extra == 'dev'
Requires-Dist: flake8 ; extra == 'dev'
Requires-Dist: sphinx ; extra == 'dev'
Requires-Dist: bump2version ; extra == 'dev'
Provides-Extra: docs
Requires-Dist: sphinx ; extra == 'docs'
Provides-Extra: numpy
Requires-Dist: numpy ; extra == 'numpy'
Provides-Extra: release
Requires-Dist: bump2version ; extra == 'release'
Provides-Extra: tests
Requires-Dist: pytest ; extra == 'tests'
Requires-Dist: pytest-mock ; extra == 'tests'
Requires-Dist: flake8 ; extra == 'tests'
Requires-Dist: numpy ; extra == 'tests'
